<?xml version="1.0" encoding="utf-8" ?>
<dwsync>
<file name="archive.png" server="ftp.nyccute.com" local="130404480740000000" remote="130998936000000000" Dst="1" />
<file name="audio.png" server="ftp.nyccute.com" local="130404480740000000" remote="130998936000000000" Dst="1" />
<file name="code.png" server="ftp.nyccute.com" local="130402698160000000" remote="130998936000000000" Dst="1" />
<file name="default.png" server="ftp.nyccute.com" local="130402698160000000" remote="130998936000000000" Dst="1" />
<file name="document.png" server="ftp.nyccute.com" local="130402698160000000" remote="130998936000000000" Dst="1" />
<file name="interactive.png" server="ftp.nyccute.com" local="130402698160000000" remote="130998936000000000" Dst="1" />
<file name="spreadsheet.png" server="ftp.nyccute.com" local="130402698160000000" remote="130998936000000000" Dst="1" />
<file name="text.png" server="ftp.nyccute.com" local="130402698160000000" remote="130998936000000000" Dst="1" />
<file name="video.png" server="ftp.nyccute.com" local="130402698160000000" remote="130998936000000000" Dst="1" />
</dwsync>