<?xml version="1.0" encoding="utf-8" ?>
<dwsync>
<file name="404.php" server="ftp.nyccute.com" local="130632264220000000" remote="130998935400000000" Dst="1" />
<file name="archive.php" server="ftp.nyccute.com" local="130627850620000000" remote="130998935400000000" Dst="1" />
<file name="comments.php" server="ftp.nyccute.com" local="130632264220000000" remote="130998935400000000" Dst="1" />
<file name="author-bio.php" server="ftp.nyccute.com" local="130632264220000000" remote="130998935400000000" Dst="1" />
<file name="content-link.php" server="ftp.nyccute.com" local="130632264220000000" remote="130998935400000000" Dst="1" />
<file name="content-page.php" server="ftp.nyccute.com" local="130632264220000000" remote="130998935400000000" Dst="1" />
<file name="content-none.php" server="ftp.nyccute.com" local="130632264220000000" remote="130998935400000000" Dst="1" />
<file name="content-search.php" server="ftp.nyccute.com" local="130632264220000000" remote="130998935400000000" Dst="1" />
<file name="content.php" server="ftp.nyccute.com" local="130632264220000000" remote="130998935400000000" Dst="1" />
<file name="footer.php" server="ftp.nyccute.com" local="130632264220000000" remote="130998935400000000" Dst="1" />
<file name="functions.php" server="ftp.nyccute.com" local="130791306860000000" remote="130998935400000000" Dst="1" />
<file name="header.php" server="ftp.nyccute.com" local="130658550220000000" remote="130998935400000000" Dst="1" />
<file name="image.php" server="ftp.nyccute.com" local="130632264220000000" remote="130998935400000000" Dst="1" />
<file name="index.php" server="ftp.nyccute.com" local="130627850620000000" remote="130998935400000000" Dst="1" />
<file name="page.php" server="ftp.nyccute.com" local="130609205060000000" remote="130998935400000000" Dst="1" />
<file name="readme.txt" server="ftp.nyccute.com" local="130939314260000000" remote="130998935400000000" Dst="1" />
<file name="rtl.css" server="ftp.nyccute.com" local="130877525660000000" remote="130998935400000000" Dst="1" />
<file name="sidebar.php" server="ftp.nyccute.com" local="130609205060000000" remote="130998935400000000" Dst="1" />
<file name="search.php" server="ftp.nyccute.com" local="130632264220000000" remote="130998935400000000" Dst="1" />
<file name="single.php" server="ftp.nyccute.com" local="130629010420000000" remote="130998935400000000" Dst="1" />
<file name="screenshot.png" server="ftp.nyccute.com" local="130590013980000000" remote="130998935400000000" Dst="1" />
<file name="style.css" server="ftp.nyccute.com" local="130939314260000000" remote="130998935400000000" Dst="1" />
</dwsync>